{
  "id": "2187798",
  "name": "tesla",
  "font_family": "iconfont",
  "css_prefix_text": "icon-",
  "description": "",
  "glyphs": [
    {
      "icon_id": "9974757",
      "name": "感叹号",
      "font_class": "gantanhao",
      "unicode": "e710",
      "unicode_decimal": 59152
    },
    {
      "icon_id": "31139",
      "name": "多云-天气",
      "font_class": "duoyun",
      "unicode": "e61d",
      "unicode_decimal": 58909
    },
    {
      "icon_id": "278744",
      "name": "下箭头",
      "font_class": "xiajiantou",
      "unicode": "e6cc",
      "unicode_decimal": 59084
    },
    {
      "icon_id": "301853",
      "name": "星星",
      "font_class": "xingxing",
      "unicode": "e632",
      "unicode_decimal": 58930
    },
    {
      "icon_id": "551966",
      "name": "箭头",
      "font_class": "arrow-right-copy-copy-copy",
      "unicode": "e604",
      "unicode_decimal": 58884
    },
    {
      "icon_id": "554435",
      "name": "网络",
      "font_class": "iconset0401",
      "unicode": "e718",
      "unicode_decimal": 59160
    },
    {
      "icon_id": "784212",
      "name": "版权",
      "font_class": "banquan",
      "unicode": "e6d5",
      "unicode_decimal": 59093
    },
    {
      "icon_id": "1915203",
      "name": "销售仪表盘",
      "font_class": "icon-test",
      "unicode": "e603",
      "unicode_decimal": 58883
    },
    {
      "icon_id": "5698508",
      "name": "上箭头",
      "font_class": "shangjiantou",
      "unicode": "e62a",
      "unicode_decimal": 58922
    },
    {
      "icon_id": "6966909",
      "name": "加",
      "font_class": "jia",
      "unicode": "e624",
      "unicode_decimal": 58916
    },
    {
      "icon_id": "11354838",
      "name": "警告",
      "font_class": "jinggao",
      "unicode": "e63b",
      "unicode_decimal": 58939
    }
  ]
}
